MANIFEST.in
README.rst
requirements.txt
setup.py
mocurly/__init__.py
mocurly/backend.py
mocurly/core.py
mocurly/endpoints.py
mocurly/errors.py
mocurly/utils.py
mocurly.egg-info/PKG-INFO
mocurly.egg-info/SOURCES.txt
mocurly.egg-info/dependency_links.txt
mocurly.egg-info/requires.txt
mocurly.egg-info/top_level.txt
mocurly/templates/account.xml
mocurly/templates/add_on.xml
mocurly/templates/adjustment.xml
mocurly/templates/billing_info.xml
mocurly/templates/coupon.xml
mocurly/templates/invoice.xml
mocurly/templates/plan.xml
mocurly/templates/redemption.xml
mocurly/templates/subscription.xml
mocurly/templates/transaction.xml
mocurly/templates/transaction_error.xml