Metadata-Version: 1.1
Name: mocurly
Version: 0.2.3
Summary: A library that allows your python tests to easily mock out the recurly library
Home-page: https://github.com/Captricity/mocurly
Author: Yoriyasu Yano
Author-email: yoriy@captricity.com
License: UNKNOWN
Download-URL: https://github.com/Captricity/mocurly/tarball/v0.2.3
Keywords: testing
Platform: UNKNOWN
